nptr_cli/__init__.py
nptr_cli/nptr.py
nptr_cli-0.5.1.dist-info/LICENSE.txt
nptr_cli-0.5.1.dist-info/METADATA
nptr_cli-0.5.1.dist-info/WHEEL
nptr_cli-0.5.1.dist-info/entry_points.txt
nptr_cli-0.5.1.dist-info/top_level.txt
nptr_cli-0.5.1.dist-info/RECORD
