Metadata-Version: 2.1
Name: nptr-cli
Version: 0.5.1
Summary: Manage your uploads to 0x0.st from the cli.
Home-page: https://github.com/jonas-w/nptr-cli
Author: Jonas Wunderlich
License: GPL-3.0-or-later
Project-URL: Documentation, https://jonas-w.github.io/nptr-cli
Project-URL: Source, https://github.com/jonas-w/nptr-cli
Project-URL: Download, https://pypi.org/project/nptr-cli
Platform: any
Classifier: Development Status :: 4 - Beta
Classifier: Programming Language :: Python
Requires-Python: >=3.0
License-File: LICENSE.txt
Requires-Dist: requests
Requires-Dist: appdirs
Requires-Dist: tomli
Requires-Dist: validators
Requires-Dist: importlib-metadata ; python_version < "3.8"
Provides-Extra: testing
Requires-Dist: setuptools ; extra == 'testing'
Requires-Dist: pytest ; extra == 'testing'
Requires-Dist: pytest-cov ; extra == 'testing'
